{
  "project_info": {
    "project_number": "69201457652",
    "project_id": "pakuni-app",
    "storage_bucket": "pakuni-app.appspot.com"
  },
  "client": [
    {
      "client_info": {
        "mobilesdk_app_id": "1:69201457652:android:f9c3d5e8a7b2c4d5f",
        "android_client_info": {
          "package_name": "com.pakuni"
        }
      },
      "oauth_client": [
        {
          "client_id": "69201457652-km6n3soj0dr4aq3m8845vboth14sm61j.apps.googleusercontent.com",
          "client_type": 1,
          "android_info": {
            "package_name": "com.pakuni",
            "certificate_hash": "ab5ca75089ca51e7b4e571f8caf0991d449ac4c1"
          }
        },
        {
          "client_id": "69201457652-q8n88n7sf55dl0sp70488agcrjctttc9.apps.googleusercontent.com",
          "client_type": 3
        }
      ],
      "api_key": [
        {
          "current_key": "AIzaSyCM8w7Ifu6jmNtze9b7MLvDtyUqYsJOEKA"
        }
      ],
      "services": {
        "appinvite_service": {
          "other_platform_oauth_client": [
            {
              "client_id": "69201457652-q8n88n7sf55dl0sp70488agcrjctttc9.apps.googleusercontent.com",
              "client_type": 3
            }
          ]
        }
      }
    }
  ],
  "configuration_version": "1"
}
